LICENSE
README.md
pyproject.toml
setup.py
llmlib/base_model_wrapper.py
llmlib/huggingface.py
llmlib/openai.py
llmlib.egg-info/PKG-INFO
llmlib.egg-info/SOURCES.txt
llmlib.egg-info/dependency_links.txt
llmlib.egg-info/requires.txt
llmlib.egg-info/top_level.txt