Metadata-Version: 2.1
Name: llmlib
Version: 0.2.0
Summary: Portability lib for OpenAI, Hugging Face, and FastChat local model APIs
Home-page: https://github.com/mark-watson/llmlib
Author: Mark Watson
Author-email: Mark Watson <markw@markwatson.com>
License: Apache License, Version 2.0
Project-URL: Homepage, https://github.com/mark-watson/llmlib
Project-URL: Bug Tracker, https://github.com/mark-watson/llmlib/issues
Classifier: Programming Language :: Python :: 3
Classifier: License :: OSI Approved :: MIT License
Classifier: Operating System :: OS Independent
Requires-Python: >=3.7
License-File: LICENSE
